firex_flame/__init__.py
firex_flame/__main__.py
firex_flame/_version.py
firex_flame/api.py
firex_flame/controller.py
firex_flame/event_broker_processor.py
firex_flame/event_file_processor.py
firex_flame/flame_helper.py
firex_flame/flame_task_graph.py
firex_flame/launcher.py
firex_flame/main_app.py
firex_flame/model_dumper.py
firex_flame/web_app.py
firex_flame/templates/index.html
firex_flame-2.6.105.dist-info/licenses/LICENSE
firex_flame-2.6.105.dist-info/METADATA
firex_flame-2.6.105.dist-info/WHEEL
firex_flame-2.6.105.dist-info/entry_points.txt
firex_flame-2.6.105.dist-info/top_level.txt
firex_flame-2.6.105.dist-info/zip-safe
firex_flame-2.6.105.dist-info/RECORD
