Metadata-Version: 2.4
Name: firex_flame
Version: 2.6.105
Summary: FireX event processor and web server.
Home-page: https://github.com/FireXStuff/firex-flame
Author: Core FireX Team
Author-email: firex-dev@gmail.com
License: BSD-3-Clause
License-File: LICENSE
Requires-Dist: Flask==3.1.0
Requires-Dist: Flask-AutoIndex==0.6.6
Requires-Dist: Werkzeug==3.1.3
Requires-Dist: python-socketio==5.3.0
Requires-Dist: firexapp
Requires-Dist: firex_flame_ui<0.30
Requires-Dist: requests
Requires-Dist: beautifulsoup4
Requires-Dist: paramiko
Requires-Dist: gevent-websocket
Requires-Dist: gevent
Requires-Dist: importlib-resources
Requires-Dist: jsonpath-ng
Requires-Dist: cryptography==42.0.7
Requires-Dist: bcrypt==4.1.3
Dynamic: author
Dynamic: author-email
Dynamic: home-page
Dynamic: license
Dynamic: license-file
Dynamic: requires-dist
Dynamic: summary
